CHANGELOG.md
MANIFEST.in
README.md
setup.cfg
setup.py
versioneer.py
src/libreflow/__init__.py
src/libreflow.extensions.runner.tvpaint_build.egg-info/PKG-INFO
src/libreflow.extensions.runner.tvpaint_build.egg-info/SOURCES.txt
src/libreflow.extensions.runner.tvpaint_build.egg-info/dependency_links.txt
src/libreflow.extensions.runner.tvpaint_build.egg-info/requires.txt
src/libreflow.extensions.runner.tvpaint_build.egg-info/top_level.txt
src/libreflow/extensions/__init__.py
src/libreflow/extensions/runner/__init__.py
src/libreflow/extensions/runner/tvpaint_build/__init__.py
src/libreflow/extensions/runner/tvpaint_build/_version.py
src/libreflow/extensions/runner/tvpaint_build/scripts/__init__.py
src/libreflow/extensions/runner/tvpaint_build/scripts/project_template.py
src/libreflow/extensions/runner/tvpaint_build/scripts/reload_audio.py