Metadata-Version: 2.1
Name: libreflow.extensions.runner.tvpaint_build
Version: 1.0.4
Home-page: https://gitlab.com/lfs.coop/libreflow/extensions/runner/tvpaint
Author: LFS
Author-email: libreflow@lfs.coop
License: LGPLv3+
Keywords: kabaret libreflow
Classifier: Programming Language :: Python :: 3
Classifier: Intended Audience :: Developers
Classifier: License :: OSI Approved :: GNU Lesser General Public License v3 or later (LGPLv3+)
Classifier: Operating System :: OS Independent
Requires-Python: >=3.9
Requires-Dist: pytvpaint
